alfred/__init__.py
alfred/core.py
alfredynhoacg_dev-0.1.0.dist-info/licenses/LICENSE
test/__init__.py
test/test_core.py
alfredynhoacg_dev-0.1.0.dist-info/METADATA
alfredynhoacg_dev-0.1.0.dist-info/WHEEL
alfredynhoacg_dev-0.1.0.dist-info/top_level.txt
alfredynhoacg_dev-0.1.0.dist-info/RECORD
