Metadata-Version: 2.4
Name: alfredynhoacg-dev
Version: 0.1.0
Summary: Mi primera librería en Python
Home-page: https://github.com/tuusuario/alfred
Author: Alfredo Callizaya Gutierrez
Author-email: alfredynho.cg@gmail.com
Classifier: Programming Language :: Python :: 3
Classifier: License :: OSI Approved :: MIT License
Classifier: Operating System :: OS Independent
Requires-Python: >=3.6
License-File: LICENSE
Dynamic: license-file
